{
  "platform": "pinball_fx2",
  "totalGames": 76,
  "lastUpdated": "2025-06-08",
  "metadata": {
    "description": "pinball_fx2 game database",
    "format": "Each game contains: id (romname only), fullpath (platform-romname), name, year, publisher, genre, rating",
    "source": "Converted from CSV format",
    "originalFile": "pinball_fx2.csv",
    "idFormat": "ID field contains only the romname (e.g., 'pacman' instead of 'mame-pacman'), fullpath contains complete identifier"
  },
  "games": [
    {
      "id": "Alien_Isolation",
      "fullpath": "pinball_fx2-Alien_Isolation",
      "name": "Alien Isolation",
      "year": "2016",
      "publisher": "Microsoft Studios",
      "genre": "Pinball",
      "rating": "ESRB - E (Everyone)"
    },
    {
      "id": "Alien_vs_Predator",
      "fullpath": "pinball_fx2-Alien_vs_Predator",
      "name": "Alien vs Predator",
      "year": "2016",
      "publisher": "Microsoft Studios",
      "genre": "Pinball",
      "rating": "ESRB - E (Everyone)"
    },
    {
      "id": "Aliens",
      "fullpath": "pinball_fx2-Aliens",
      "name": "Aliens",
      "year": "2016",
      "publisher": "Microsoft Studios",
      "genre": "Pinball",
      "rating": "ESRB - E (Everyone)"
    },
    {
      "id": "AmericanDad",
      "fullpath": "pinball_fx2-AmericanDad",
      "name": "American Dad!",
      "year": "2015",
      "publisher": "Microsoft Studios",
      "genre": "Pinball",
      "rating": "ESRB - E (Everyone)"
    },
    {
      "id": "Archer",
      "fullpath": "pinball_fx2-Archer",
      "name": "Archer",
      "year": "2015",
      "publisher": "Microsoft Studios",
      "genre": "Pinball",
      "rating": "ESRB - E (Everyone)"
    },
    {
      "id": "BioLab",
      "fullpath": "pinball_fx2-BioLab",
      "name": "Biolab",
      "year": "2013",
      "publisher": "Microsoft Studios",
      "genre": "Pinball",
      "rating": "ESRB - E (Everyone)"
    },
    {
      "id": "BobsBurgers",
      "fullpath": "pinball_fx2-BobsBurgers",
      "name": "Bob's Burgers",
      "year": "2015",
      "publisher": "Microsoft Studios",
      "genre": "Pinball",
      "rating": "ESRB - E (Everyone)"
    },
    {
      "id": "CastleStorm",
      "fullpath": "pinball_fx2-CastleStorm",
      "name": "CastleStorm",
      "year": "2015",
      "publisher": "Microsoft Studios",
      "genre": "Pinball",
      "rating": "ESRB - E (Everyone)"
    },
    {
      "id": "BETHESDA_Doom",
      "fullpath": "pinball_fx2-BETHESDA_Doom",
      "name": "DOOM",
      "year": "2016",
      "publisher": "Microsoft Studios",
      "genre": "Pinball",
      "rating": "ESRB - E (Everyone)"
    },
    {
      "id": "EarthDefense",
      "fullpath": "pinball_fx2-EarthDefense",
      "name": "Earth Defense",
      "year": "2013",
      "publisher": "Microsoft Studios",
      "genre": "Pinball",
      "rating": "ESRB - E (Everyone)"
    },
    {
      "id": "Eldorado",
      "fullpath": "pinball_fx2-Eldorado",
      "name": "El Dorado",
      "year": "2013",
      "publisher": "Microsoft Studios",
      "genre": "Pinball",
      "rating": "ESRB - E (Everyone)"
    },
    {
      "id": "Looter",
      "fullpath": "pinball_fx2-Looter",
      "name": "Epic Quest",
      "year": "2013",
      "publisher": "Microsoft Studios",
      "genre": "Pinball",
      "rating": "ESRB - E (Everyone)"
    },
    {
      "id": "Excalibur",
      "fullpath": "pinball_fx2-Excalibur",
      "name": "Excalibur",
      "year": "2013",
      "publisher": "Microsoft Studios",
      "genre": "Pinball",
      "rating": "ESRB - E (Everyone)"
    },
    {
      "id": "BETHESDA_Fallout",
      "fullpath": "pinball_fx2-BETHESDA_Fallout",
      "name": "Fallout",
      "year": "2016",
      "publisher": "Microsoft Studios",
      "genre": "Pinball",
      "rating": "ESRB - E (Everyone)"
    },
    {
      "id": "FamilyGuy",
      "fullpath": "pinball_fx2-FamilyGuy",
      "name": "Family Guy",
      "year": "2015",
      "publisher": "Microsoft Studios",
      "genre": "Pinball",
      "rating": "ESRB - E (Everyone)"
    },
    {
      "id": "Football_Milan",
      "fullpath": "pinball_fx2-Football_Milan",
      "name": "Football Super League - A.C. Milan",
      "year": "2014",
      "publisher": "Microsoft Studios",
      "genre": "Pinball",
      "rating": "ESRB - E (Everyone)"
    },
    {
      "id": "Football_Roma",
      "fullpath": "pinball_fx2-Football_Roma",
      "name": "Football Super League - A.S. Roma",
      "year": "2014",
      "publisher": "Microsoft Studios",
      "genre": "Pinball",
      "rating": "ESRB - E (Everyone)"
    },
    {
      "id": "Football_Arsenal",
      "fullpath": "pinball_fx2-Football_Arsenal",
      "name": "Football Super League - Arsenal",
      "year": "2014",
      "publisher": "Microsoft Studios",
      "genre": "Pinball",
      "rating": "ESRB - E (Everyone)"
    },
    {
      "id": "Football_Barcelona",
      "fullpath": "pinball_fx2-Football_Barcelona",
      "name": "Football Super League - FC Barcelona",
      "year": "2014",
      "publisher": "Microsoft Studios",
      "genre": "Pinball",
      "rating": "ESRB - E (Everyone)"
    },
    {
      "id": "Football_Juventus",
      "fullpath": "pinball_fx2-Football_Juventus",
      "name": "Football Super League - Juventus",
      "year": "2014",
      "publisher": "Microsoft Studios",
      "genre": "Pinball",
      "rating": "ESRB - E (Everyone)"
    },
    {
      "id": "Football_Liverpool",
      "fullpath": "pinball_fx2-Football_Liverpool",
      "name": "Football Super League - Liverpool F.C.",
      "year": "2014",
      "publisher": "Microsoft Studios",
      "genre": "Pinball",
      "rating": "ESRB - E (Everyone)"
    },
    {
      "id": "Football_RealMadrid",
      "fullpath": "pinball_fx2-Football_RealMadrid",
      "name": "Football Super League - Real Madrid C.F.",
      "year": "2014",
      "publisher": "Microsoft Studios",
      "genre": "Pinball",
      "rating": "ESRB - E (Everyone)"
    },
    {
      "id": "Football",
      "fullpath": "pinball_fx2-Football",
      "name": "Football Super League - Zen Studios F.C.",
      "year": "2014",
      "publisher": "Microsoft Studios",
      "genre": "Pinball",
      "rating": "ESRB - E (Everyone)"
    },
    {
      "id": "Mars",
      "fullpath": "pinball_fx2-Mars",
      "name": "Mars",
      "year": "2013",
      "publisher": "Microsoft Studios",
      "genre": "Pinball",
      "rating": "ESRB - E (Everyone)"
    },
    {
      "id": "MARVEL_Ant-Man",
      "fullpath": "pinball_fx2-MARVEL_Ant-Man",
      "name": "Marvel - Ant-Man",
      "year": "2015",
      "publisher": "Microsoft Studios",
      "genre": "Pinball",
      "rating": "ESRB - E (Everyone)"
    },
    {
      "id": "MARVEL_Blade",
      "fullpath": "pinball_fx2-MARVEL_Blade",
      "name": "Marvel - Blade",
      "year": "2013",
      "publisher": "Microsoft Studios",
      "genre": "Pinball",
      "rating": "ESRB - E (Everyone)"
    },
    {
      "id": "MARVEL_CaptainAmerica",
      "fullpath": "pinball_fx2-MARVEL_CaptainAmerica",
      "name": "Marvel - Captain America",
      "year": "2013",
      "publisher": "Microsoft Studios",
      "genre": "Pinball",
      "rating": "ESRB - E (Everyone)"
    },
    {
      "id": "MARVEL_CivilWar",
      "fullpath": "pinball_fx2-MARVEL_CivilWar",
      "name": "Marvel - Civil War",
      "year": "2013",
      "publisher": "Microsoft Studios",
      "genre": "Pinball",
      "rating": "ESRB - E (Everyone)"
    },
    {
      "id": "MARVEL_Deadpool",
      "fullpath": "pinball_fx2-MARVEL_Deadpool",
      "name": "Marvel - Deadpool",
      "year": "2014",
      "publisher": "Microsoft Studios",
      "genre": "Pinball",
      "rating": "ESRB - E (Everyone)"
    },
    {
      "id": "MARVEL_DrStrange",
      "fullpath": "pinball_fx2-MARVEL_DrStrange",
      "name": "Marvel - Doctor Strange",
      "year": "2013",
      "publisher": "Microsoft Studios",
      "genre": "Pinball",
      "rating": "ESRB - E (Everyone)"
    },
    {
      "id": "MARVEL_FantasticFour",
      "fullpath": "pinball_fx2-MARVEL_FantasticFour",
      "name": "Marvel - Fantastic Four",
      "year": "2013",
      "publisher": "Microsoft Studios",
      "genre": "Pinball",
      "rating": "ESRB - E (Everyone)"
    },
    {
      "id": "MARVEL_FearItSelf",
      "fullpath": "pinball_fx2-MARVEL_FearItSelf",
      "name": "Marvel - Fear Itself",
      "year": "2013",
      "publisher": "Microsoft Studios",
      "genre": "Pinball",
      "rating": "ESRB - E (Everyone)"
    },
    {
      "id": "MARVEL_GhostRider",
      "fullpath": "pinball_fx2-MARVEL_GhostRider",
      "name": "Marvel - Ghost Rider",
      "year": "2013",
      "publisher": "Microsoft Studios",
      "genre": "Pinball",
      "rating": "ESRB - E (Everyone)"
    },
    {
      "id": "MARVEL_Guardians",
      "fullpath": "pinball_fx2-MARVEL_Guardians",
      "name": "Marvel - Guardians of the Galaxy",
      "year": "2014",
      "publisher": "Microsoft Studios",
      "genre": "Pinball",
      "rating": "ESRB - E10+ (Everyone 10+)"
    },
    {
      "id": "MARVEL_IronMan",
      "fullpath": "pinball_fx2-MARVEL_IronMan",
      "name": "Marvel - Iron Man",
      "year": "2013",
      "publisher": "Microsoft Studios",
      "genre": "Pinball",
      "rating": "ESRB - E (Everyone)"
    },
    {
      "id": "MARVEL_MoonKnight",
      "fullpath": "pinball_fx2-MARVEL_MoonKnight",
      "name": "Marvel - Moon Knight",
      "year": "2013",
      "publisher": "Microsoft Studios",
      "genre": "Pinball",
      "rating": "ESRB - E (Everyone)"
    },
    {
      "id": "MARVEL_MsMarvel",
      "fullpath": "pinball_fx2-MARVEL_MsMarvel",
      "name": "Marvel - A-Force",
      "year": "2016",
      "publisher": "Microsoft Studios",
      "genre": "Pinball",
      "rating": "ESRB - E (Everyone)"
    },
    {
      "id": "MARVEL_SpiderMan",
      "fullpath": "pinball_fx2-MARVEL_SpiderMan",
      "name": "Marvel - Spider-Man",
      "year": "2013",
      "publisher": "Microsoft Studios",
      "genre": "Pinball",
      "rating": "ESRB - E (Everyone)"
    },
    {
      "id": "MARVEL_Avengers",
      "fullpath": "pinball_fx2-MARVEL_Avengers",
      "name": "Marvel - The Avengers",
      "year": "2013",
      "publisher": "Microsoft Studios",
      "genre": "Pinball",
      "rating": "ESRB - E (Everyone)"
    },
    {
      "id": "MARVEL_Age_of_Ultron",
      "fullpath": "pinball_fx2-MARVEL_Age_of_Ultron",
      "name": "Marvel - The Avengers Age of Ultron",
      "year": "2015",
      "publisher": "Microsoft Studios",
      "genre": "Pinball",
      "rating": "ESRB - E (Everyone)"
    },
    {
      "id": "MARVEL_InfinityGauntlet",
      "fullpath": "pinball_fx2-MARVEL_InfinityGauntlet",
      "name": "Marvel - The Infinity Gauntlet",
      "year": "2013",
      "publisher": "Microsoft Studios",
      "genre": "Pinball",
      "rating": "ESRB - E (Everyone)"
    },
    {
      "id": "MARVEL_Thor",
      "fullpath": "pinball_fx2-MARVEL_Thor",
      "name": "Marvel - Thor",
      "year": "2013",
      "publisher": "Microsoft Studios",
      "genre": "Pinball",
      "rating": "ESRB - E (Everyone)"
    },
    {
      "id": "MARVEL_Venom",
      "fullpath": "pinball_fx2-MARVEL_Venom",
      "name": "Marvel - Venom",
      "year": "2014",
      "publisher": "Microsoft Studios",
      "genre": "Pinball",
      "rating": "ESRB - E (Everyone)"
    },
    {
      "id": "MARVEL_Wolverine",
      "fullpath": "pinball_fx2-MARVEL_Wolverine",
      "name": "Marvel - Wolverine",
      "year": "2013",
      "publisher": "Microsoft Studios",
      "genre": "Pinball",
      "rating": "ESRB - E (Everyone)"
    },
    {
      "id": "MARVEL_WOP_TheNextGeneration",
      "fullpath": "pinball_fx2-MARVEL_WOP_TheNextGeneration",
      "name": "Marvel - Champions",
      "year": "2016",
      "publisher": "Microsoft Studios",
      "genre": "Pinball",
      "rating": "ESRB - E (Everyone)"
    },
    {
      "id": "MARVEL_WWH",
      "fullpath": "pinball_fx2-MARVEL_WWH",
      "name": "Marvel - World War Hulk",
      "year": "2013",
      "publisher": "Microsoft Studios",
      "genre": "Pinball",
      "rating": "ESRB - E (Everyone)"
    },
    {
      "id": "MARVEL_XMen",
      "fullpath": "pinball_fx2-MARVEL_XMen",
      "name": "Marvel - X-Men",
      "year": "2013",
      "publisher": "Microsoft Studios",
      "genre": "Pinball",
      "rating": "ESRB - E (Everyone)"
    },
    {
      "id": "SplosionMan",
      "fullpath": "pinball_fx2-SplosionMan",
      "name": "Ms. Splosion Man",
      "year": "2013",
      "publisher": "Microsoft Studios",
      "genre": "Pinball",
      "rating": "ESRB - E (Everyone)"
    },
    {
      "id": "Paranormal",
      "fullpath": "pinball_fx2-Paranormal",
      "name": "Paranormal",
      "year": "2013",
      "publisher": "Microsoft Studios",
      "genre": "Pinball",
      "rating": "ESRB - E (Everyone)"
    },
    {
      "id": "Pasha",
      "fullpath": "pinball_fx2-Pasha",
      "name": "Pasha",
      "year": "2013",
      "publisher": "Microsoft Studios",
      "genre": "Pinball",
      "rating": "ESRB - E (Everyone)"
    },
    {
      "id": "PlantsVsZombies",
      "fullpath": "pinball_fx2-PlantsVsZombies",
      "name": "Plants vs. Zombies",
      "year": "2014",
      "publisher": "Microsoft Studios",
      "genre": "Pinball",
      "rating": "ESRB - E (Everyone)"
    },
    {
      "id": "Portal",
      "fullpath": "pinball_fx2-Portal",
      "name": "Portal",
      "year": "2015",
      "publisher": "Microsoft Studios",
      "genre": "Pinball",
      "rating": "ESRB - E (Everyone)"
    },
    {
      "id": "Rome",
      "fullpath": "pinball_fx2-Rome",
      "name": "Rome",
      "year": "2013",
      "publisher": "Microsoft Studios",
      "genre": "Pinball",
      "rating": "ESRB - E (Everyone)"
    },
    {
      "id": "Atlantis",
      "fullpath": "pinball_fx2-Atlantis",
      "name": "Secrets of the Deep",
      "year": "2013",
      "publisher": "Microsoft Studios",
      "genre": "Pinball",
      "rating": "ESRB - E (Everyone)"
    },
    {
      "id": "Shaman",
      "fullpath": "pinball_fx2-Shaman",
      "name": "Shaman",
      "year": "2013",
      "publisher": "Microsoft Studios",
      "genre": "Pinball",
      "rating": "ESRB - E (Everyone)"
    },
    {
      "id": "BETHESDA_Skyrim",
      "fullpath": "pinball_fx2-BETHESDA_Skyrim",
      "name": "Skyrim",
      "year": "2016",
      "publisher": "Microsoft Studios",
      "genre": "Pinball",
      "rating": "ESRB - E (Everyone)"
    },
    {
      "id": "Citadel",
      "fullpath": "pinball_fx2-Citadel",
      "name": "Sorcerer's Lair",
      "year": "2013",
      "publisher": "Microsoft Studios",
      "genre": "Pinball",
      "rating": "ESRB - E (Everyone)"
    },
    {
      "id": "SouthPark2",
      "fullpath": "pinball_fx2-SouthPark2",
      "name": "South Park - Butters' Very Own Pinball Game",
      "year": "2014",
      "publisher": "Microsoft Studios",
      "genre": "Pinball",
      "rating": "ESRB - E (Everyone)"
    },
    {
      "id": "SouthPark1",
      "fullpath": "pinball_fx2-SouthPark1",
      "name": "South Park - Super Sweet Pinball",
      "year": "2014",
      "publisher": "Microsoft Studios",
      "genre": "Pinball",
      "rating": "ESRB - E (Everyone)"
    },
    {
      "id": "STARWARS_Episode_4",
      "fullpath": "pinball_fx2-STARWARS_Episode_4",
      "name": "Star Wars - A New Hope",
      "year": "2014",
      "publisher": "Microsoft Studios",
      "genre": "Pinball",
      "rating": "ESRB - E (Everyone)"
    },
    {
      "id": "STARWARS_Boba_Fett",
      "fullpath": "pinball_fx2-STARWARS_Boba_Fett",
      "name": "Star Wars - Boba Fett",
      "year": "2013",
      "publisher": "Microsoft Studios",
      "genre": "Pinball",
      "rating": "ESRB - E (Everyone)"
    },
    {
      "id": "STARWARS_Darth_Vader",
      "fullpath": "pinball_fx2-STARWARS_Darth_Vader",
      "name": "Star Wars - Darth Vader",
      "year": "2013",
      "publisher": "Microsoft Studios",
      "genre": "Pinball",
      "rating": "ESRB - E10+ (Everyone 10+)"
    },
    {
      "id": "STARWARS_Droids",
      "fullpath": "pinball_fx2-STARWARS_Droids",
      "name": "Star Wars - Droids",
      "year": "2014",
      "publisher": "Microsoft Studios",
      "genre": "Pinball",
      "rating": "ESRB - E (Everyone)"
    },
    {
      "id": "STARWARS_Episode_7",
      "fullpath": "pinball_fx2-STARWARS_Episode_7",
      "name": "Star Wars - The Force Awakens",
      "year": "2016",
      "publisher": "Microsoft Studios",
      "genre": "Pinball",
      "rating": "ESRB - E (Everyone)"
    },
    {
      "id": "STARWARS_Han_Solo",
      "fullpath": "pinball_fx2-STARWARS_Han_Solo",
      "name": "Star Wars - Han Solo",
      "year": "2014",
      "publisher": "Microsoft Studios",
      "genre": "Pinball",
      "rating": "ESRB - E (Everyone)"
    },
    {
      "id": "STARWARS_Light_VS_Dark",
      "fullpath": "pinball_fx2-STARWARS_Light_VS_Dark",
      "name": "Star Wars - Masters of the Force",
      "year": "2014",
      "publisher": "Microsoft Studios",
      "genre": "Pinball",
      "rating": "ESRB - E (Everyone)"
    },
    {
      "id": "STARWARS_MFO",
      "fullpath": "pinball_fx2-STARWARS_MFO",
      "name": "Star Wars - Might of the First Order",
      "year": "2014",
      "publisher": "Microsoft Studios",
      "genre": "Pinball",
      "rating": "ESRB - E (Everyone)"
    },
    {
      "id": "STARWARS_Rebels",
      "fullpath": "pinball_fx2-STARWARS_Rebels",
      "name": "Star Wars - Rebels",
      "year": "2015",
      "publisher": "Microsoft Studios",
      "genre": "Pinball",
      "rating": "ESRB - E10+ (Everyone 10+)"
    },
    {
      "id": "STARWARS_Episode_6",
      "fullpath": "pinball_fx2-STARWARS_Episode_6",
      "name": "Star Wars - Return of the Jedi",
      "year": "2013",
      "publisher": "Microsoft Studios",
      "genre": "Pinball",
      "rating": "ESRB - E10+ (Everyone 10+)"
    },
    {
      "id": "STARWARS_SFA",
      "fullpath": "pinball_fx2-STARWARS_SFA",
      "name": "Star Wars - Starfighter Assault",
      "year": "2013",
      "publisher": "Microsoft Studios",
      "genre": "Pinball",
      "rating": "ESRB - E10+ (Everyone 10+)"
    },
    {
      "id": "STARWARS_CloneWars",
      "fullpath": "pinball_fx2-STARWARS_CloneWars",
      "name": "Star Wars - The Clone Wars",
      "year": "2013",
      "publisher": "Microsoft Studios",
      "genre": "Pinball",
      "rating": "ESRB - E (Everyone)"
    },
    {
      "id": "STARWARS_Episode_5",
      "fullpath": "pinball_fx2-STARWARS_Episode_5",
      "name": "Star Wars - The Empire Strikes Back",
      "year": "2013",
      "publisher": "Microsoft Studios",
      "genre": "Pinball",
      "rating": "ESRB - E (Everyone)"
    },
    {
      "id": "Tesla",
      "fullpath": "pinball_fx2-Tesla",
      "name": "Tesla",
      "year": "2013",
      "publisher": "Microsoft Studios",
      "genre": "Pinball",
      "rating": "ESRB - E (Everyone)"
    },
    {
      "id": "V12",
      "fullpath": "pinball_fx2-V12",
      "name": "V12",
      "year": "2013",
      "publisher": "Microsoft Studios",
      "genre": "Pinball",
      "rating": "ESRB - E (Everyone)"
    },
    {
      "id": "TheWalkingDead",
      "fullpath": "pinball_fx2-TheWalkingDead",
      "name": "The Walking Dead",
      "year": "2014",
      "publisher": "Microsoft Studios",
      "genre": "Pinball",
      "rating": "ESRB - E (Everyone)"
    },
    {
      "id": "Western",
      "fullpath": "pinball_fx2-Western",
      "name": "Wild West Rampage",
      "year": "2015",
      "publisher": "Microsoft Studios",
      "genre": "Pinball",
      "rating": "ESRB - E (Everyone)"
    }
  ]
}